pyqwe/__init__.py
pyqwe/exceptions.py
pyqwe/helpers.py
pyqwe/parser.py
pyqwe/printer.py
pyqwe-3.1.1.dist-info/entry_points.txt
pyqwe-3.1.1.dist-info/licenses/LICENSE
pyqwe-3.1.1.dist-info/WHEEL
pyqwe-3.1.1.dist-info/METADATA
pyqwe-3.1.1.dist-info/RECORD
