Metadata-Version: 2.4
Name: pyqwe
Version: 3.1.1
Summary: Run commands quickly from the pyproject.toml (or pyqwe.toml) file.
Author-email: David Carmichael <david@uilix.com>
Requires-Python: >=3.9
Classifier: License :: OSI Approved :: MIT License
License-File: LICENSE
Project-URL: Source, https://github.com/CheeseCake87/pyqwe
